rlm_toolkit/__init__.py
rlm_toolkit/freshness.py
rlm_toolkit/indexer.py
rlm_toolkit/agentic/__init__.py
rlm_toolkit/agentic/reasoning.py
rlm_toolkit/agentic/rewards.py
rlm_toolkit/agents/__init__.py
rlm_toolkit/agents/advanced.py
rlm_toolkit/agents/core.py
rlm_toolkit/callbacks/__init__.py
rlm_toolkit/cli/__init__.py
rlm_toolkit/cli/commands.py
rlm_toolkit/cli/main.py
rlm_toolkit/core/__init__.py
rlm_toolkit/core/callbacks.py
rlm_toolkit/core/config.py
rlm_toolkit/core/context.py
rlm_toolkit/core/engine.py
rlm_toolkit/core/exceptions.py
rlm_toolkit/core/recovery.py
rlm_toolkit/core/repl.py
rlm_toolkit/core/state.py
rlm_toolkit/core/streaming.py
rlm_toolkit/crystal/__init__.py
rlm_toolkit/crystal/ast_extractor.py
rlm_toolkit/crystal/compression.py
rlm_toolkit/crystal/extractor.py
rlm_toolkit/crystal/hierarchy.py
rlm_toolkit/crystal/indexer.py
rlm_toolkit/crystal/relations.py
rlm_toolkit/crystal/safe.py
rlm_toolkit/crystal/summarizer.py
rlm_toolkit/embeddings/__init__.py
rlm_toolkit/embeddings/extended.py
rlm_toolkit/evaluation/__init__.py
rlm_toolkit/evaluation/benchmarks.py
rlm_toolkit/evaluation/framework.py
rlm_toolkit/evaluation/metrics.py
rlm_toolkit/evaluation/nih_benchmark.py
rlm_toolkit/evolve/__init__.py
rlm_toolkit/evolve/self_evolving.py
rlm_toolkit/loaders/__init__.py
rlm_toolkit/loaders/advanced.py
rlm_toolkit/loaders/extended.py
rlm_toolkit/loaders/extended2.py
rlm_toolkit/loaders/extended3.py
rlm_toolkit/mcp/__init__.py
rlm_toolkit/mcp/__main__.py
rlm_toolkit/mcp/contexts.py
rlm_toolkit/mcp/providers.py
rlm_toolkit/mcp/ratelimit.py
rlm_toolkit/mcp/server.py
rlm_toolkit/memory/__init__.py
rlm_toolkit/memory/base.py
rlm_toolkit/memory/buffer.py
rlm_toolkit/memory/crypto.py
rlm_toolkit/memory/episodic.py
rlm_toolkit/memory/hierarchical.py
rlm_toolkit/memory/secure.py
rlm_toolkit/memory_bridge/__init__.py
rlm_toolkit/memory_bridge/manager.py
rlm_toolkit/memory_bridge/mcp_tools.py
rlm_toolkit/memory_bridge/mcp_tools_v2.py
rlm_toolkit-2.3.0.dist-info/licenses/LICENSE
rlm_toolkit-2.3.0.dist-info/METADATA
rlm_toolkit-2.3.0.dist-info/WHEEL
rlm_toolkit-2.3.0.dist-info/entry_points.txt
rlm_toolkit-2.3.0.dist-info/top_level.txt
rlm_toolkit-2.3.0.dist-info/RECORD
