Metadata-Version: 2.4
Name: rlm-toolkit
Version: 2.3.0
Summary: Recursive Language Models Toolkit for processing unlimited context
Author-email: SENTINEL Community <rlm@sentinel.dev>
License: Apache-2.0
Project-URL: Homepage, https://github.com/DmitrL-dev/AISecurity/tree/main/sentinel-community/rlm-toolkit
Project-URL: Documentation, https://github.com/DmitrL-dev/AISecurity/tree/main/sentinel-community/rlm-toolkit/docs
Project-URL: Repository, https://github.com/DmitrL-dev/AISecurity
Project-URL: Issues, https://github.com/DmitrL-dev/AISecurity/issues
Project-URL: Changelog, https://github.com/DmitrL-dev/AISecurity/blob/main/sentinel-community/rlm-toolkit/CHANGELOG.md
Keywords: llm,recursive,language-models,long-context,rlm
Classifier: Development Status :: 5 - Production/Stable
Classifier: Intended Audience :: Developers
Classifier: License :: OSI Approved :: Apache Software License
Classifier: Programming Language :: Python :: 3
Classifier: Programming Language :: Python :: 3.10
Classifier: Programming Language :: Python :: 3.11
Classifier: Programming Language :: Python :: 3.12
Classifier: Topic :: Scientific/Engineering :: Artificial Intelligence
Requires-Python: >=3.10
License-File: LICENSE
Requires-Dist: pyyaml>=6.0
Provides-Extra: openai
Requires-Dist: openai>=1.0; extra == "openai"
Provides-Extra: anthropic
Requires-Dist: anthropic>=0.20; extra == "anthropic"
Provides-Extra: google
Requires-Dist: google-generativeai>=0.5; extra == "google"
Provides-Extra: ollama
Requires-Dist: ollama>=0.1; extra == "ollama"
Provides-Extra: langfuse
Requires-Dist: langfuse>=2.0; extra == "langfuse"
Provides-Extra: langsmith
Requires-Dist: langsmith>=0.1; extra == "langsmith"
Provides-Extra: mcp
Requires-Dist: mcp>=1.0; extra == "mcp"
Requires-Dist: httpx>=0.25; extra == "mcp"
Provides-Extra: semantic
Requires-Dist: sentence-transformers>=2.2.0; extra == "semantic"
Requires-Dist: spacy>=3.7.0; extra == "semantic"
Provides-Extra: security
Requires-Dist: cryptography>=41.0.0; extra == "security"
Provides-Extra: full
Requires-Dist: sentence-transformers>=2.2.0; extra == "full"
Requires-Dist: cryptography>=41.0.0; extra == "full"
Requires-Dist: spacy>=3.7.0; extra == "full"
Provides-Extra: all
Requires-Dist: openai>=1.0; extra == "all"
Requires-Dist: anthropic>=0.20; extra == "all"
Requires-Dist: google-generativeai>=0.5; extra == "all"
Requires-Dist: ollama>=0.1; extra == "all"
Requires-Dist: langfuse>=2.0; extra == "all"
Requires-Dist: langsmith>=0.1; extra == "all"
Requires-Dist: mcp>=1.0; extra == "all"
Requires-Dist: httpx>=0.25; extra == "all"
Requires-Dist: sentence-transformers>=2.2.0; extra == "all"
Requires-Dist: cryptography>=41.0.0; extra == "all"
Requires-Dist: spacy>=3.7.0; extra == "all"
Provides-Extra: dev
Requires-Dist: pytest>=7.0; extra == "dev"
Requires-Dist: pytest-cov>=4.0; extra == "dev"
Requires-Dist: pytest-asyncio>=0.21; extra == "dev"
Requires-Dist: ruff>=0.1; extra == "dev"
Requires-Dist: mypy>=1.0; extra == "dev"
Requires-Dist: bandit>=1.7; extra == "dev"
Requires-Dist: build>=1.0; extra == "dev"
Requires-Dist: twine>=4.0; extra == "dev"
Dynamic: license-file
